qtest_reporter/__init__.py
qtest_reporter/logger.py
qtest_reporter/qtest.py
qtest_reporter/requester.py
qtest_reporter/api/__init__.py
qtest_reporter/api/login.py
qtest_reporter/api/project.py
qtest_reporter/api/test_case.py
qtest_reporter/api/test_cycle.py
qtest_reporter/api/test_log.py
qtest_reporter/api/test_run.py
qtest_reporter/api/test_suite.py
qtest_reporter/api/user_profile.py
qtest_reporter-0.0.11.dist-info/LICENSE
qtest_reporter-0.0.11.dist-info/METADATA
qtest_reporter-0.0.11.dist-info/WHEEL
qtest_reporter-0.0.11.dist-info/top_level.txt
qtest_reporter-0.0.11.dist-info/RECORD
