Metadata-Version: 2.1
Name: qtest-reporter
Version: 0.0.11
Summary: qtest_reporter is a tool that allows you to easily report the results of your automated testing to qTest test management tool.
Author-email: Volodymyr Zyhmund <volodymyr.romanovych@gmail.com>
Classifier: Development Status :: 3 - Alpha
Classifier: Intended Audience :: Developers
Classifier: License :: Freeware
Classifier: Operating System :: POSIX :: Linux
Classifier: Programming Language :: Python :: 3 :: Only
Classifier: Natural Language :: English
Classifier: Topic :: Software Development :: Testing
Requires-Python: >=3.8
License-File: LICENSE
Requires-Dist: requests (>=2.31.0)
